pycronado/core.py
pycronado/rate_limiter.py
pycronado/token.py
pycronado/util.py
pycronado-0.1.12.dist-info/licenses/LICENSE
pycronado-0.1.12.dist-info/METADATA
pycronado-0.1.12.dist-info/WHEEL
pycronado-0.1.12.dist-info/top_level.txt
pycronado-0.1.12.dist-info/RECORD
