Metadata-Version: 2.4
Name: pycronado
Version: 0.1.12
Summary: Set of trivial tools for building microservices with Tornado
Author-email: inaimathi <leo.zovic@gmail.com>
Project-URL: Homepage, https://github.com/inaimathi/pycronado
Project-URL: Issues, https://github.com/inaimathi/pycronado/issues
Classifier: Programming Language :: Python :: 3
Classifier: License :: OSI Approved :: MIT License
Classifier: Operating System :: OS Independent
Requires-Python: >=3.8
License-File: LICENSE
Requires-Dist: tornado
Requires-Dist: pyjwt[crypto]
Requires-Dist: fakeredis==2.32.0
Dynamic: license-file
